CLHkidai/__init__.py
CLHkidai/_version.py
CLHkidai/client.py
CLHkidai/errors.py
CLHkidai/prompts.py
CLHkidai/safety.py
clhkidai-0.1.4.dist-info/licenses/LICENSE
clhkidai-0.1.4.dist-info/METADATA
clhkidai-0.1.4.dist-info/WHEEL
clhkidai-0.1.4.dist-info/entry_points.txt
clhkidai-0.1.4.dist-info/top_level.txt
clhkidai-0.1.4.dist-info/RECORD
